Metadata-Version: 2.4
Name: livekit-plugins-turn-detector
Version: 1.3.11
Summary: End of utterance detection for LiveKit Agents
Project-URL: Documentation, https://docs.livekit.io
Project-URL: Website, https://livekit.io/
Project-URL: Source, https://github.com/livekit/agents
Author-email: LiveKit <hello@livekit.io>
License-Expression: Apache-2.0
Keywords: ai,audio,livekit,realtime,video,voice,webrtc
Classifier: Intended Audience :: Developers
Classifier: License :: OSI Approved :: Apache Software License
Classifier: Programming Language :: Python :: 3
Classifier: Programming Language :: Python :: 3 :: Only
Classifier: Programming Language :: Python :: 3.9
Classifier: Programming Language :: Python :: 3.10
Classifier: Topic :: Multimedia :: Sound/Audio
Classifier: Topic :: Multimedia :: Video
Classifier: Topic :: Scientific/Engineering :: Artificial Intelligence
Requires-Python: >=3.9.0
Requires-Dist: jinja2
Requires-Dist: livekit-agents>=1.3.11
Requires-Dist: numpy>=1.26
Requires-Dist: onnxruntime>=1.18
Requires-Dist: transformers<=4.57.1,>=4.47.1
